wickdata/__init__.py
wickdata/builders/__init__.py
wickdata/builders/candle_query_builder.py
wickdata/builders/data_request_builder.py
wickdata/core/__init__.py
wickdata/core/data_manager.py
wickdata/core/data_streamer.py
wickdata/core/errors.py
wickdata/core/event_emitter.py
wickdata/core/wickdata.py
wickdata/database/__init__.py
wickdata/database/base.py
wickdata/database/candle_repository.py
wickdata/database/database_factory.py
wickdata/database/models.py
wickdata/database/sqlite_database.py
wickdata/exchanges/__init__.py
wickdata/exchanges/exchange_adapter.py
wickdata/exchanges/exchange_manager.py
wickdata/models/__init__.py
wickdata/models/candle.py
wickdata/models/config.py
wickdata/models/data_gap.py
wickdata/models/data_range.py
wickdata/models/data_request.py
wickdata/models/dataset_info.py
wickdata/models/dataset_metadata.py
wickdata/models/gap_coverage.py
wickdata/models/historical_data_stats.py
wickdata/models/progress_info.py
wickdata/models/stream_options.py
wickdata/models/timeframe.py
wickdata/models/validation_result.py
wickdata/services/__init__.py
wickdata/services/data_fetcher_service.py
wickdata/services/data_validation_service.py
wickdata/services/gap_analysis_service.py
wickdata/services/retry_service.py
wickdata/utils/__init__.py
wickdata/utils/config_helpers.py
wickdata/utils/logger.py
wickdata/utils/timeframe_utils.py
wickdata/utils/validation.py
wickdata-0.1.0.dist-info/licenses/LICENSE
wickdata-0.1.0.dist-info/METADATA
wickdata-0.1.0.dist-info/WHEEL
wickdata-0.1.0.dist-info/top_level.txt
wickdata-0.1.0.dist-info/RECORD
