Metadata-Version: 2.4
Name: wickdata
Version: 0.1.0
Summary: High-performance library for fetching, storing, and streaming historical cryptocurrency market data
Author-email: h2337 <hikmat2337@gmail.com>
License: MIT
Project-URL: Homepage, https://github.com/h2337/wickdata
Project-URL: Repository, https://github.com/h2337/wickdata
Project-URL: Bug Tracker, https://github.com/h2337/wickdata/issues
Keywords: cryptocurrency,trading,market-data,backtesting,ohlcv,ccxt
Classifier: Development Status :: 4 - Beta
Classifier: Intended Audience :: Developers
Classifier: Intended Audience :: Financial and Insurance Industry
Classifier: License :: OSI Approved :: MIT License
Classifier: Programming Language :: Python :: 3
Classifier: Programming Language :: Python :: 3.9
Classifier: Programming Language :: Python :: 3.10
Classifier: Programming Language :: Python :: 3.11
Classifier: Programming Language :: Python :: 3.12
Classifier: Programming Language :: Python :: 3.13
Classifier: Topic :: Office/Business :: Financial :: Investment
Classifier: Topic :: Software Development :: Libraries :: Python Modules
Requires-Python: >=3.9
License-File: LICENSE
Requires-Dist: ccxt>=4.0.0
Requires-Dist: sqlalchemy>=2.0.0
Requires-Dist: alembic>=1.12.0
Requires-Dist: pydantic>=2.0.0
Requires-Dist: aiohttp>=3.9.0
Requires-Dist: python-dateutil>=2.8.0
Requires-Dist: pytz>=2023.3
Requires-Dist: aiosqlite>=0.19.0
Provides-Extra: dev
Requires-Dist: pytest>=7.4.0; extra == "dev"
Requires-Dist: pytest-asyncio>=0.21.0; extra == "dev"
Requires-Dist: pytest-cov>=4.1.0; extra == "dev"
Requires-Dist: black>=23.0.0; extra == "dev"
Requires-Dist: mypy>=1.5.0; extra == "dev"
Requires-Dist: ruff>=0.1.0; extra == "dev"
Dynamic: license-file
